.gitignore
LICENSE
MANIFEST.in
README.rst
TODO
release.py
setup.py
setup.sh
test.py
doc/Makefile
doc/conf.py
doc/cppcheck_detailed.png
doc/cppcheck_source.png
doc/cppcheck_summary.png
doc/credits.rst
doc/history.rst
doc/index.rst
doc/installation.rst
doc/make.bat
doc/modules.rst
doc/overview.rst
doc/support.rst
doc/usage.rst
doc/waftools.rst
playground/.gitignore
playground/README
playground/ccenv.ini
playground/indent.pro
playground/pkg.py
playground/wscript
playground/components/chello/.gitignore
playground/components/chello/wscript
playground/components/chello/include/hello.h
playground/components/chello/src/hello.c
playground/components/ciambad/.gitignore
playground/components/ciambad/cppcheck.suppress
playground/components/ciambad/wscript
playground/components/ciambad/src/iambad.c
playground/components/cleaking/.gitignore
playground/components/cleaking/wscript
playground/components/cleaking/include/leaking.h
playground/components/cleaking/src/leaking.c
playground/components/clib/program/.gitignore
playground/components/clib/program/wscript
playground/components/clib/program/src/program.c
playground/components/clib/shared/.gitignore
playground/components/clib/shared/wscript
playground/components/clib/shared/include/bar.h
playground/components/clib/shared/src/bar.c
playground/components/clib/static/.gitignore
playground/components/clib/static/wscript
playground/components/clib/static/include/foo.h
playground/components/clib/static/src/foo.c
playground/components/cmath/.gitignore
playground/components/cmath/wscript
playground/components/cmath/src/cmath.c
playground/components/cnested/aos/t/wscript
playground/components/cnested/aos/t/src/t.c
playground/components/cnested/aos/x/wscript
playground/components/cnested/aos/x/include/x.h
playground/components/cnested/aos/x/src/x.c
playground/components/cnested/aos/y/wscript
playground/components/cnested/aos/y/include/y.h
playground/components/cnested/aos/y/src/y.c
playground/components/cnested/aos/z/wscript
waftools.egg-info/PKG-INFO
waftools.egg-info/SOURCES.txt
waftools.egg-info/dependency_links.txt
waftools.egg-info/entry_points.txt
waftools.egg-info/requires.txt
waftools.egg-info/top_level.txt