Metadata-Version: 1.1
Name: waftools
Version: 0.4.13
Summary: Handy tools for the WAF meta build environment
Home-page: https://bitbucket.org/Moo7/waftools
Author: Michel Mooij
Author-email: michel.mooij7@gmail.com
License: MIT
Download-URL: https://bitbucket.org/Moo7/waftools/downloads/waftools-0.4.13.tar.gz
Keywords: waf,c,c++,cppcheck,codeblocks,eclipse,make,cmake,msdev,doxygen,GNU indent
Platform: any
Classifier: Development Status :: 4 - Beta
Classifier: Environment :: Console
Classifier: Intended Audience :: Developers
Classifier: License :: OSI Approved :: MIT License
Classifier: Operating System :: Microsoft :: Windows :: Windows 7
Classifier: Operating System :: Microsoft :: Windows :: Windows Vista
Classifier: Operating System :: Microsoft :: Windows :: Windows XP
Classifier: Operating System :: POSIX :: Linux
Classifier: Programming Language :: C
Classifier: Programming Language :: C++
Classifier: Programming Language :: Python :: 2.7
Classifier: Programming Language :: Python :: 3.4
Classifier: Topic :: Software Development :: Build Tools
Classifier: Topic :: Software Development :: Embedded Systems
Classifier: Topic :: Utilities
